saclay_format/__init__.py
saclay_format/compute_densities.py
saclay_format/ev1_to_cr1.py
saclay_format/ev8_to_ev1.py
saclay_format/hdf5_yaml_converter.py
saclay_format/saclay_parser.py
saclay_format/visualisation_ascii.py
saclay_format/visualisation_rho.py
saclay_format/visualisation_rho_TD.py
saclay_format-0.2.15.dist-info/licenses/LICENSE
saclay_format-0.2.15.dist-info/METADATA
saclay_format-0.2.15.dist-info/WHEEL
saclay_format-0.2.15.dist-info/entry_points.txt
saclay_format-0.2.15.dist-info/top_level.txt
saclay_format-0.2.15.dist-info/RECORD
