Metadata-Version: 2.4
Name: saclay-format
Version: 0.2.15
Summary: python parser and usefull script related to the saclay format
Maintainer-email: Guillaume Scamps <guillaume.scamps@l2it.in2p3.fr>, David Regnier <David.REGNIER@cea.fr>, Wouter Ryssens <Wouter.Ryssens@ulb.be>
License-Expression: GPL-3.0-only
Project-URL: Sources, https://gitlab.com/regnier/Saclay_format
Requires-Python: >=3.10
License-File: LICENSE
Requires-Dist: h5py
Requires-Dist: numpy
Requires-Dist: pyyaml
Provides-Extra: visu
Requires-Dist: matplotlib; extra == "visu"
Requires-Dist: PyQt5; extra == "visu"
Requires-Dist: scipy; extra == "visu"
Requires-Dist: scikit-image; extra == "visu"
Dynamic: license-file
